MANIFEST.in
README.md
setup.py
FastGets.egg-info/PKG-INFO
FastGets.egg-info/SOURCES.txt
FastGets.egg-info/dependency_links.txt
FastGets.egg-info/entry_points.txt
FastGets.egg-info/not-zip-safe
FastGets.egg-info/requires.txt
FastGets.egg-info/top_level.txt
fastgets/__init__.py
fastgets/bloomfilter.py
fastgets/env.py
fastgets/job.py
fastgets/process.py
fastgets/task.py
fastgets/utils.py
fastgets/work.py
fastgets/core/__init__.py
fastgets/core/client.py
fastgets/core/cmd.py
fastgets/core/decorators.py
fastgets/core/errors.py
fastgets/core/log.py
fastgets/engine/__init__.py
fastgets/engine/base.py
fastgets/engine/distributed.py
fastgets/engine/local.py
fastgets/headers/__init__.py
fastgets/headers/cookie.py
fastgets/headers/proxy.py
fastgets/headers/user_agent.py
fastgets/models/__init__.py
fastgets/models/instance.py
fastgets/models/script_log.py
fastgets/models/unknown_error.py
fastgets/parse/__init__.py
fastgets/parse/item.py
fastgets/parse/parser.py
fastgets/parse/site.py
fastgets/parse/utils.py
fastgets/pool/__init__.py
fastgets/pool/error.py
fastgets/pool/pending.py
fastgets/pool/repeat.py
fastgets/pool/running.py
fastgets/pool/warning.py
fastgets/script/__init__.py
fastgets/script/log.py
fastgets/script/script.py
fastgets/stats/__init__.py
fastgets/stats/cluster.py
fastgets/stats/instance.py
fastgets/stats/time_counter.py
fastgets/template/__init__.py
fastgets/template/base.py
fastgets/template/template.py
fastgets/web/__init__.py
fastgets/web/app.py
fastgets/web/static/index.html
fastgets/web/static/dist/0.cfdecd31e78dbd4eddd8.chunk.js
fastgets/web/static/dist/05acfdb568b3df49ad31355b19495d4a.woff
fastgets/web/static/dist/1.cfdecd31e78dbd4eddd8.chunk.js
fastgets/web/static/dist/2.cfdecd31e78dbd4eddd8.chunk.js
fastgets/web/static/dist/24712f6c47821394fba7942fbb52c3b2.ttf
fastgets/web/static/dist/2c2ae068be3b089e0a5b59abb1831550.eot
fastgets/web/static/dist/3.cfdecd31e78dbd4eddd8.chunk.js
fastgets/web/static/dist/4.cfdecd31e78dbd4eddd8.chunk.js
fastgets/web/static/dist/5.cfdecd31e78dbd4eddd8.chunk.js
fastgets/web/static/dist/6.cfdecd31e78dbd4eddd8.chunk.js
fastgets/web/static/dist/621bd386841f74e0053cb8e67f8a0604.svg
fastgets/web/static/dist/7.cfdecd31e78dbd4eddd8.chunk.js
