Metadata-Version: 1.0
Name: FastGets
Version: 0.3.4
Summary: Python Crawling Framework for Humans
Home-page: https://github.com/ShuJuHeiKe/FastGets
Author: XuYong
Author-email: tonyxuourlove@gmail.com
License: BSD
Platform: UNKNOWN
